school_algorithms/__init__.py
school_algorithms/_if_not_valid_raise.py
school_algorithms/circle.py
school_algorithms/lcm.py
school_algorithms/physics.py
school_algorithms/pyramid.py
school_algorithms/pythagorus.py
school_algorithms/trapezium.py
school_algorithms/triangle.py
school_algorithms-1.14.0.dist-info/LICENSE
school_algorithms-1.14.0.dist-info/METADATA
school_algorithms-1.14.0.dist-info/WHEEL
school_algorithms-1.14.0.dist-info/top_level.txt
school_algorithms-1.14.0.dist-info/RECORD
