Metadata-Version: 2.1
Name: school-algorithms
Version: 1.14.0
Summary: School algorithm module for Python
Home-page: https://github.com/Sammygarch/school_algorithms.git
Author: Sammy Garcia
Author-email: s@mmygarcia.com
License: UNKNOWN
Project-URL: Bug Tracker, https://github.com/Sammygarch/school_algorithms/issues
Platform: UNKNOWN
Classifier: Programming Language :: Python :: 3
Classifier: Development Status :: 5 - Production/Stable
Classifier: Operating System :: OS Independent
Classifier: License :: OSI Approved :: MIT License
Requires-Python: >=3
License-File: LICENSE
